{
  "days" : [
    {
      "sessions" : [

      ],
      "minuteCount" : 144,
      "pickupCount" : 87,
      "pickups" : [

      ],
      "appUsages" : [

      ],
      "date" : "2018-05-23T00:00:00-04:00"
    },
    {
      "sessions" : [

      ],
      "minuteCount" : 123,
      "pickupCount" : 92,
      "pickups" : [

      ],
      "appUsages" : [

      ],
      "date" : "2018-05-22T00:00:00-04:00"
    },
    {
      "sessions" : [

      ],
      "minuteCount" : 116,
      "pickupCount" : 81,
      "pickups" : [

      ],
      "appUsages" : [

      ],
      "date" : "2018-05-21T00:00:00-04:00"
    },
    {
      "sessions" : [

      ],
      "minuteCount" : 223,
      "pickupCount" : 154,
      "pickups" : [

      ],
      "appUsages" : [

      ],
      "date" : "2018-05-20T00:00:00-04:00"
    },
    {
      "sessions" : [

      ],
      "minuteCount" : 94,
      "pickupCount" : 56,
      "pickups" : [

      ],
      "appUsages" : [

      ],
      "date" : "2018-05-19T00:00:00-04:00"
    },
    {
      "sessions" : [

      ],
      "minuteCount" : 176,
      "pickupCount" : 145,
      "pickups" : [

      ],
      "appUsages" : [

      ],
      "date" : "2018-05-18T00:00:00-04:00"
    },
    {
      "sessions" : [

      ],
      "minuteCount" : 187,
      "pickupCount" : 189,
      "pickups" : [

      ],
      "appUsages" : [

      ],
      "date" : "2018-05-17T00:00:00-04:00"
    }
  ]
}